secrets_vault/__init__.py
secrets_vault/__main__.py
secrets_vault/backends.py
secrets_vault/constants.py
secrets_vault/exceptions.py
secrets_vault/formatters.py
secrets_vault/vault.py
secrets_vault/version.py
secrets_vault-0.2.8.dist-info/LICENSE
secrets_vault-0.2.8.dist-info/METADATA
secrets_vault-0.2.8.dist-info/WHEEL
secrets_vault-0.2.8.dist-info/entry_points.txt
secrets_vault-0.2.8.dist-info/top_level.txt
secrets_vault-0.2.8.dist-info/RECORD
