Metadata-Version: 2.1
Name: secrets-vault
Version: 0.2.8
Summary: Simple encrypted secrets for Python
Home-page: https://github.com/anthonynsimon/secrets-vault
Author: Anthony N. Simon
License: MIT
Platform: UNKNOWN
Classifier: License :: OSI Approved :: MIT License
Classifier: Programming Language :: Python
Classifier: Programming Language :: Python :: 3.9
Classifier: Topic :: Software Development :: Libraries :: Python Modules
License-File: LICENSE
Requires-Dist: cryptography (>=38.0.4)
Requires-Dist: click (>=8.1.6)
Requires-Dist: pydash (>=7.0.5)
Requires-Dist: ruamel.yaml (>=0.17.32)
